energyplus_api_helpers/__init__.py
energyplus_api_helpers/import_helper.py
energyplus_api_helpers/demos/01_simple_library_call.py
energyplus_api_helpers/demos/02_threaded.py
energyplus_api_helpers/demos/03_multiprocessed.py
energyplus_api_helpers/demos/04_dynamic_terminal_output_progress.py
energyplus_api_helpers/demos/05_dynamic_terminal_output.py
energyplus_api_helpers/demos/06_plot_e_plus.py
energyplus_api_helpers/demos/07_server.py
energyplus_api_helpers/demos/07_server_index.html
energyplus_api_helpers/demos/08_server_advanced.py
energyplus_api_helpers/demos/08_server_advanced_index.html
energyplus_api_helpers/demos/__init__.py
energyplus_api_helpers-0.4.dist-info/LICENSE.txt
energyplus_api_helpers-0.4.dist-info/METADATA
energyplus_api_helpers-0.4.dist-info/WHEEL
energyplus_api_helpers-0.4.dist-info/top_level.txt
energyplus_api_helpers-0.4.dist-info/RECORD
