Metadata-Version: 2.1
Name: energyplus-api-helpers
Version: 0.4
Summary: A set of helper classes, functions and demos, for interacting with the EnergyPlus Python API
Home-page: https://github.com/Myoldmopar/EnergyPlusAPIHelper
Author: Edwin Lee, for NREL, for the United States Department of Energy
License: ModifiedBSD
Keywords: energyplus_launch,ep_launch,EnergyPlus,eplus,Energy+,Building Simulation,Whole Building Energy Simulation,Heat Transfer,HVAC,Modeling
Platform: Linux (Tested on Ubuntu)
Platform: MacOSX
Platform: Windows
Classifier: Development Status :: 4 - Beta
Classifier: Intended Audience :: Science/Research
Classifier: Natural Language :: English
Classifier: Operating System :: OS Independent
Classifier: Programming Language :: Python :: 3 :: Only
Classifier: Topic :: Scientific/Engineering
Classifier: Topic :: Scientific/Engineering :: Physics
Classifier: Topic :: Utilities
Requires-Dist: matplotlib
Requires-Dist: flask
Requires-Dist: pysparklines
Requires-Dist: asciichartpy
